ot_my_libs/ArgsParse.py
ot_my_libs/FileActions.py
ot_my_libs/MyCalculate.py
ot_my_libs/PlugsHelper.py
ot_my_libs/PlugsHelperTest_plug1_a.py
ot_my_libs/PlugsHelperTest_plug2_a.py
ot_my_libs/PlugsHelperTest_plug3_a.py
ot_my_libs/TimeHelper.py
ot_my_libs/XMLHelper.py
ot_my_libs/__init__.py
ot_my_libs/db_helper.py
ot_my_libs/example.py
ot_my_libs/myFastPlot.py
ot_my_libs/myLoger.py
ot_my_libs/myMqttClient.py
ot_my_libs/mysql_helper.py
ot_my_libs-0.0.14.dist-info/LICENSE.txt
ot_my_libs-0.0.14.dist-info/METADATA
ot_my_libs-0.0.14.dist-info/WHEEL
ot_my_libs-0.0.14.dist-info/top_level.txt
ot_my_libs-0.0.14.dist-info/RECORD
