Metadata-Version: 2.1
Name: ot-my-libs
Version: 0.0.14
Summary: oiyshTerminal my basic libs: myLoger | FileActions | PlugsHelper | MyCalculate | db_helper | mysql_helper | ...
Author-email: Bartlomiej Ceglik <yoyoek@wp.pl>
Project-URL: Homepage, https://github.com/yOyOeK1/oiyshTerminal/tree/main/OTPIPS/ot_my_libs
Project-URL: Bug Tracker, https://github.com/yOyOeK1/oiyshTerminal/labels/ot_my_libs
Classifier: Development Status :: 3 - Alpha
Classifier: Programming Language :: Python :: 3
Classifier: License :: OSI Approved :: MIT License
Requires-Python: >=3.7
License-File: LICENSE.txt
Requires-Dist: pymysql
Requires-Dist: paho-mqtt (==1.5.0)
